phast/__init__.py
phast/constants.py
phast/phastcpp.cp39-win_amd64.pyd
phast/phastcpp.pyi
phast/threshold_profile.py
phast/data/I_det_121.npy
phast/data/cochlear18_0.npy
phast/data/cochlear25_8.npy
phast/data/df120.npy
phast/data/freedom_avg_response_data.npy
phast/data/idet.npy
phast/data/pulse_train_121.npy
phast/data/sounds/AzBio_3sent.wav
phast/data/sounds/AzBio_3sent_65dBSPL.wav
phast/data/sounds/BobbyBareDropKickMeJesus.wav
phast/data/sounds/Choice.wav
phast/data/sounds/IFFM-V1.0_60s_16bit.wav
phast/data/sounds/L001s04r.wav
phast/data/sounds/asa.wav
phast/data/sounds/chirp.wav
phast/data/sounds/defineit.wav
phast/data/sounds/impulse.wav
phast/data/sounds/olnoise.wav
phast/data/sounds/sheep.wav
phast/data/sounds/tone_1kHz.wav
phast/data/sounds/vacuum_cleaner.wav
phast/scs/__init__.py
phast/scs/ab/__init__.py
phast/scs/ab/audio_ramp.py
phast/scs/ab/audiomixer.py
phast/scs/ab/automatic_gain_control.py
phast/scs/ab/buffer.py
phast/scs/ab/defaults.py
phast/scs/ab/electrodogram.py
phast/scs/ab/filterbank.py
phast/scs/ab/frontend.py
phast/scs/ab/mapping.py
phast/scs/ab/noise_reduction.py
phast/scs/ab/post_filterbank.py
phast/scs/ab/vocoder.py
phast/scs/ace/__init__.py
phast/scs/ace/agc.py
phast/scs/ace/audio.py
phast/scs/ace/filterbank.py
phast/scs/ace/lgf.py
phast/scs/ace/mapping.py
phast/scs/ace/parameters.py
phast/scs/ace/utility.py
phastc-1.1.5.dist-info/licenses/LICENSE
tests/__init__.py
tests/test_din_file.py
tests/test_neurogram.py
tests/test_phast.py
tests/test_problem.py
tests/test_scs_ab.py
tests/test_scs_ace.py
tests/test_spont_activity.py
tests/test_threading.py
tests/test_threshold_profile.py
phastc-1.1.5.dist-info/METADATA
phastc-1.1.5.dist-info/WHEEL
phastc-1.1.5.dist-info/top_level.txt
phastc-1.1.5.dist-info/RECORD
