Metadata-Version: 2.4
Name: phastc
Version: 1.1.5
Summary: Phenomological Adaptive STochastic auditory nerve fiber model
Author: Jacob de Nobel
License-File: LICENSE
Requires-Dist: matplotlib
Requires-Dist: numpy
Requires-Dist: librosa
Dynamic: author
Dynamic: description
Dynamic: description-content-type
Dynamic: license-file
Dynamic: requires-dist
Dynamic: summary
